setup.py
ac_ptk.egg-info/PKG-INFO
ac_ptk.egg-info/SOURCES.txt
ac_ptk.egg-info/dependency_links.txt
ac_ptk.egg-info/entry_points.txt
ac_ptk.egg-info/requires.txt
ac_ptk.egg-info/top_level.txt
ac_ptk.egg-info/test/__init__.py
performance/__init__.py
performance/android.py
performance/android_device.py
performance/chart.py
performance/checkstyle.py
performance/config.py
performance/db_helper.py
performance/excelx.py
performance/lint.py
performance/log.py
performance/mail.py
performance/matlab_plt.py
performance/mem_history.py
performance/properties.py
performance/ptk.py
performance/thread.py
performance/util.py