Metadata-Version: 1.0
Name: ac-ptk
Version: 0.1.5
Summary: android performance tests kit
Home-page: http://appinstall.aiyoumi.com:8282/qinchao/ptk.git
Author: chao
Author-email: qinchao@aicaigroup.com
License: MIT
Keywords: android,memory,performance,auto testing
Platform: POSIX
